language_agent/__init__.py
language_agent/module.py
language_agent/prompt.py
language_agent-0.3.dist-info/METADATA
language_agent-0.3.dist-info/WHEEL
language_agent-0.3.dist-info/top_level.txt
language_agent-0.3.dist-info/RECORD
