Metadata-Version: 2.1
Name: language-agent
Version: 0.3
Requires-Dist: openai
Requires-Dist: python-dotenv
